single_consumer_queue/__init__.py
single_consumer_queue/py.typed
single_consumer_queue/queue.py
single_consumer_queue-1.1.1.dist-info/LICENSE
single_consumer_queue-1.1.1.dist-info/WHEEL
single_consumer_queue-1.1.1.dist-info/METADATA
single_consumer_queue-1.1.1.dist-info/RECORD
