Metadata-Version: 2.1
Name: single-consumer-queue
Version: 1.1.1
Summary: Asyncio high-performance single consumer queue
Home-page: https://github.com/LukasKrocek/single-consumer-queue-python
License: MIT
Author: Lukas Krocek
Author-email: krocek.lukas@email.cz
Requires-Python: >=3.10,<4.0
Classifier: License :: OSI Approved :: MIT License
Classifier: Programming Language :: Python :: 3
Classifier: Programming Language :: Python :: 3.10
Classifier: Programming Language :: Python :: 3.11
